{
	"geode": "4.4.0",
	"gd": {
		"win": "2.2074",
		"android": "2.2074",
		"mac": "2.2074",
		"ios": "2.2074"
	},
	"id": "silverstar.legacy-particles",
	"name": "True Legacy Particles",
	"version": "v1.1.1",
	"developer": "SILVERSTAR",
	"description": "old player particles",
	"links": {
		"source": "https://github.com/silver984/True-Legacy-Particles"
	},
	"tags": [
		"offline",
		"customization",
		"gameplay"
	],
	"settings": {
		"legacy-tracking": {
			"name": "Legacy Tracking",
			"type": "bool",
			"description": "Restores how ground particles followed the player.",
			"default": true
		},
		"legacy-scaling": {
			"name": "Legacy Scaling",
			"type": "bool",
			"description": "Restores how particles followed the player when mini mode was first introduced.",
			"default": false
		},
		"legacy-land": {
			"name": "Legacy Land",
			"type": "bool",
			"description": "Disables rotation.",
			"default": true
		},
		"inconst-values": {
			"name": "Inconsistent Values",
			"type": "bool",
			"description": "Restores how particles change after entering certain portals.",
			"default": true
		},
		"center-dash": {
			"name": "Centered Dash Particles",
			"type": "bool",
			"default": true
		}
	}
}